LICENSE.txt
MANIFEST.in
README
requirements.txt
setup.py
styx/__init__.py
styx/redisPool.py
styx/styxConnection.py
styx/styxQueue.py
styx.egg-info/PKG-INFO
styx.egg-info/SOURCES.txt
styx.egg-info/dependency_links.txt
styx.egg-info/requires.txt
styx.egg-info/top_level.txt