Metadata-Version: 1.0
Name: styx
Version: 0.1.2
Summary: Distributed message queue based on Redis
Home-page: http://pypi.python.org/pypi/styx/
Author: Abhinav Ajgaonkar
Author-email: abhinav316@gmail.com
License: Copyright 2013 Abhinav Ajgaonkar
